{"cameraMode":{"drawMode":0,"name":"Shaded","section":"Shading Mode"},"sceneLighting":false,"audioPlay":false,"sceneViewState":{"showFog":true,"showMaterialUpdate":false,"showSkybox":false,"showFlares":true,"showImageEffects":true,"showParticleSystems":true},"in2DMode":false,"pivot":{"x":-0.268137663602829,"y":1.955803394317627,"z":1.2987275123596192},"rotation":{"x":0.12486792355775833,"y":-0.7422628402709961,"z":0.14430314302444459,"w":0.6424108743667603},"size":1.3649845123291016,"orthographic":false}